LICENSE
MANIFEST.in
README.md
api_compatibility.py
api_compatibility.txt
pyproject.toml
setup.py
examples/example_collections.py
examples/example_simulator_model.py
kimpy/KIM_ChargeUnit_bind.cpp
kimpy/KIM_CollectionItemType_bind.cpp
kimpy/KIM_Collection_bind.cpp
kimpy/KIM_Collections_bind.cpp
kimpy/KIM_ComputeArgumentName_bind.cpp
kimpy/KIM_ComputeArguments_bind.cpp
kimpy/KIM_ComputeCallbackName_bind.cpp
kimpy/KIM_DataType_bind.cpp
kimpy/KIM_EnergyUnit_bind.cpp
kimpy/KIM_LanguageName_bind.cpp
kimpy/KIM_LengthUnit_bind.cpp
kimpy/KIM_LogVerbosity_bind.cpp
kimpy/KIM_Log_bind.cpp
kimpy/KIM_ModelRoutineName_bind.cpp
kimpy/KIM_Model_bind.cpp
kimpy/KIM_Numbering_bind.cpp
kimpy/KIM_SemVer_bind.cpp
kimpy/KIM_SimulatorModel_bind.cpp
kimpy/KIM_SpeciesName_bind.cpp
kimpy/KIM_SupportStatus_bind.cpp
kimpy/KIM_TemperatureUnit_bind.cpp
kimpy/KIM_TimeUnit_bind.cpp
kimpy/__init__.py
kimpy/callbacks.hpp
kimpy/err.py
kimpy/py_kim_wrapper.h
kimpy/sim_buffer.h
kimpy.egg-info/PKG-INFO
kimpy.egg-info/SOURCES.txt
kimpy.egg-info/dependency_links.txt
kimpy.egg-info/not-zip-safe
kimpy.egg-info/requires.txt
kimpy.egg-info/top_level.txt
kimpy/neighlist/helper.hpp
kimpy/neighlist/neighbor_list.cpp
kimpy/neighlist/neighbor_list.h
kimpy/neighlist/neighbor_list_bind.cpp
scripts/KIM_FieldName_bind.cpp-template
scripts/generate_CollectionItemType_bind_test.py
scripts/generate_Collection_bind_test.py
scripts/generate_ComputeCallbackName_bind_test.py
scripts/generate_DataType_bind_test.py
scripts/generate_LanguageName_bind_test.py
scripts/generate_LogVerbosity_bind_test.py
scripts/generate_ModelRoutineName_bind_test.py
scripts/generate_Numbering_bind_test.py
scripts/generate_SpeciesName_bind_test.py
scripts/generate_SupportStatus_bind_test.py
scripts/generate_UnitSystem_bind_test.py
scripts/generate_all.py
scripts/generate_bind_test_commons.py
scripts/test_field_name.py-template
tests/test_callbacks.py
tests/test_charge_unit.py
tests/test_collection.py
tests/test_collection_item_type.py
tests/test_compute_argument_name.py
tests/test_compute_callback_name.py
tests/test_data_type.py
tests/test_energy_unit.py
tests/test_language_name.py
tests/test_length_unit.py
